loci/__init__.py
loci/analytics.py
loci/clustering.py
loci/index.py
loci/io.py
loci/plots.py
loci/topics.py
slipo_loci-0.1.4.dist-info/LICENSE
slipo_loci-0.1.4.dist-info/METADATA
slipo_loci-0.1.4.dist-info/WHEEL
slipo_loci-0.1.4.dist-info/top_level.txt
slipo_loci-0.1.4.dist-info/RECORD
