Metadata-Version: 2.1
Name: slipo-loci
Version: 0.1.4
Summary: A high-level library for analyzing Points and Areas of Interest
Home-page: https://github.com/SLIPO-EU/loci
Author: Panagiotis Kalampokis, Dimitris Skoutas
Author-email: pkalampokis@athenarc.gr, dskoutas@athenarc.gr
License: UNKNOWN
Platform: UNKNOWN
Requires-Dist: geopandas
Requires-Dist: shapely
Requires-Dist: pandas
Requires-Dist: numpy
Requires-Dist: matplotlib
Requires-Dist: folium
Requires-Dist: scikit-learn
Requires-Dist: hdbscan
Requires-Dist: scipy
Requires-Dist: networkx
Requires-Dist: wordcloud
Requires-Dist: pysal
Requires-Dist: pyLDAvis
Requires-Dist: mlxtend
Requires-Dist: osmnx
Requires-Dist: requests
